pyManson/__init__.py
pyManson/mansonClass.py
pyManson-1.2.1.dist-info/LICENSE
pyManson-1.2.1.dist-info/METADATA
pyManson-1.2.1.dist-info/WHEEL
pyManson-1.2.1.dist-info/top_level.txt
pyManson-1.2.1.dist-info/RECORD
