Metadata-Version: 2.1
Name: pyManson
Version: 1.2.1
Summary: Communcation package for Manson power supply
Author: Konstantin Niehaus
Author-email: konstantin+pypi@niehaus-web.com
License: MIT
Keywords: power supply,manson,serial
Classifier: Development Status :: 4 - Beta
Classifier: Programming Language :: Python :: 3
Classifier: Topic :: System :: Hardware
Classifier: Topic :: System :: Hardware :: Hardware Drivers
Classifier: Topic :: Scientific/Engineering
License-File: LICENSE
Requires-Dist: pyserial
